flay-0.1.0a1.dist-info/METADATA
flay-0.1.0a1.dist-info/WHEEL
flay-0.1.0a1.dist-info/entry_points.txt
flay-0.1.0a1.dist-info/licenses/LICENSE
flay/__init__.py
flay/__main__.py
flay/backend/README.md
flay/backend/__init__.py
flay/bundle/README.md
flay/bundle/__init__.py
flay/bundle/collector.py
flay/bundle/exc.py
flay/bundle/package.py
flay/cli/README.md
flay/cli/__init__.py
flay/cli/app.py
flay/cli/debug/__init__.py
flay/cli/debug/bundle.py
flay/common/__init__.py
flay/common/exc.py
flay/common/libcst.py
flay/common/logging.py
flay/common/module_spec.py
flay/minify/README.md
flay/minify/__init__.py
flay/py.typed
flay/treeshake/README.md
flay/treeshake/__init__.py
flay-0.1.0a1.dist-info/RECORD
