Metadata-Version: 2.1
Name: flay
Version: 0.1.0a1
Summary: Bundle, treeshake and minify your python projects
Author-Email: Jan Vollmer <jan@vllmr.dev>
License: MIT
Requires-Python: >=3.9
Requires-Dist: stdlib-list>=0.10.0
Requires-Dist: libcst>=1.4.0
Requires-Dist: typer>=0.12.5
Requires-Dist: rich>=13.8.1
Requires-Dist: typing-extensions>=4.12.2
Requires-Dist: platformdirs>=4.3.6
Requires-Dist: colorama>=0.4.6
